bhagyashree/__constants.py
bhagyashree/__dependencies.py
bhagyashree/__init__.py
bhagyashree/__utils.py
bhagyashree/art.py
bhagyashree/ascii_art.py
bhagyashree/error.py
bhagyashree/main.py
bhagyashree/message.py
bhagyashree/music.py
bhagyashree/utils.py
bhagyashree/video.py
bhagyashree/assets/data.json
fkvit/__constants.py
fkvit/__init__.py
fkvit/__utils.py
fkvit/ascii_art.py
fkvit/gpt.py
fkvit/main.py
fkvit/test.py
fkvit/utils.py
fkvit/assets/data.json
fkvit-0.1.0.dist-info/LICENSE
fkvit-0.1.0.dist-info/METADATA
fkvit-0.1.0.dist-info/WHEEL
fkvit-0.1.0.dist-info/entry_points.txt
fkvit-0.1.0.dist-info/top_level.txt
fkvit-0.1.0.dist-info/RECORD
