Metadata-Version: 2.1
Name: fkvit
Version: 0.1.0
Summary: IF A PROBLEM CAN BE SOLVED, THEN IT'S NOT WORTH WORRYING ABOUT.
Author: hello kitty
License: MIT
Classifier: Programming Language :: Python :: 3
Classifier: License :: OSI Approved :: MIT License
Classifier: Operating System :: OS Independent
License-File: LICENSE
Requires-Dist: pyperclip
Requires-Dist: google-generativeai
